tavern_aws/__init__.py
tavern_aws/schema.yaml
tavern_aws/session.py
tavern_aws/tavernhook.py
tavern_aws-1.1.0.dist-info/LICENSE
tavern_aws-1.1.0.dist-info/METADATA
tavern_aws-1.1.0.dist-info/WHEEL
tavern_aws-1.1.0.dist-info/entry_points.txt
tavern_aws-1.1.0.dist-info/RECORD
