Metadata-Version: 2.3
Name: tavern-aws
Version: 1.1.0
Summary: HTTP plugin for Tavern with AWS4Auth
Keywords: testing,pytest,tavern,aws
Author: Alexander Eresov
Author-email: aeresov@gmail.com
Requires-Python: >=3.11,<4.0
Classifier: Development Status :: 5 - Production/Stable
Classifier: Framework :: Pytest
Classifier: Intended Audience :: Developers
Classifier: License :: OSI Approved :: MIT License
Classifier: Programming Language :: Python :: 3
Classifier: Programming Language :: Python :: 3.11
Classifier: Topic :: Software Development :: Testing
Requires-Dist: requests-aws4auth (>=1.3.1,<2.0.0)
Requires-Dist: tavern (>=2.15.0,<3.0.0)
Project-URL: Homepage, https://github.com/aeresov/tavern-aws
